{
  "swagger": "2.0",
  "info": {
    "title": "proto/note_service.proto",
    "version": "version not set"
  },
  "tags": [
    {
      "name": "NoteApiService"
    }
  ],
  "consumes": [
    "application/json"
  ],
  "produces": [
    "application/json"
  ],
  "paths": {
    "/api/v3/notes": {
      "get": {
        "summary": "load all notes",
        "operationId": "NoteApiService_getAllNotes",
        "responses": {
          "200": {
            "description": "A successful response.",
            "schema": {
              "$ref": "#/definitions/pbGetAllNotesResponse"
            }
          },
          "default": {
            "description": "An unexpected error response.",
            "schema": {
              "$ref": "#/definitions/rpcStatus"
            }
          }
        },
        "tags": [
          "NoteApiService"
        ]
      }
    }
  },
  "definitions": {
    "pbGetAllNotesResponse": {
      "type": "object",
      "properties": {
        "notes": {
          "type": "array",
          "items": {
            "type": "object",
            "$ref": "#/definitions/pbNote"
          }
        }
      }
    },
    "pbNote": {
      "type": "object",
      "properties": {
        "id": {
          "type": "integer",
          "format": "int32"
        },
        "username": {
          "type": "string"
        },
        "timestamp": {
          "type": "string"
        },
        "text": {
          "type": "string"
        }
      }
    },
    "protobufAny": {
      "type": "object",
      "properties": {
        "@type": {
          "type": "string"
        }
      },
      "additionalProperties": {}
    },
    "rpcStatus": {
      "type": "object",
      "properties": {
        "code": {
          "type": "integer",
          "format": "int32"
        },
        "message": {
          "type": "string"
        },
        "details": {
          "type": "array",
          "items": {
            "type": "object",
            "$ref": "#/definitions/protobufAny"
          }
        }
      }
    }
  }
}
